Metadata-Version: 2.1
Name: ColoraPy
Version: 0.1.0
Summary: wsp
Home-page: https://github.com/YuxOnTop/ColoraPy
Author: ColoraPy
Author-email: tiktok.agn@gmail.com
License: MIT license
Keywords: ColoraPy
Platform: UNKNOWN
Classifier: Development Status :: 2 - Pre-Alpha
Classifier: License :: OSI Approved :: MIT License
Classifier: Natural Language :: English
Classifier: Programming Language :: Python :: 3
Requires-Python: >=3.6
License-File: LICENSE
